dataframe_handlers/__init__.py
dataframe_handlers/base/__init__.py
dataframe_handlers/base/base.py
dataframe_handlers/dask_handler/__init__.py
dataframe_handlers/dask_handler/dask_handler.py
dataframe_handlers/pandas_handler/__init__.py
dataframe_handlers/pandas_handler/pandas_handler.py
dataframe_handlers/vaex_handler/__init__.py
dataframe_handlers/vaex_handler/vaex_handler.py
dataframe_handlers/xarray_handler/__init__.py
dataframe_handlers/xarray_handler/xarray_handler.py
dataframe_handlers-0.0.5.dist-info/LICENSE
dataframe_handlers-0.0.5.dist-info/METADATA
dataframe_handlers-0.0.5.dist-info/WHEEL
dataframe_handlers-0.0.5.dist-info/top_level.txt
dataframe_handlers-0.0.5.dist-info/RECORD
