Metadata-Version: 2.1
Name: dataframe-handlers
Version: 0.0.5
Summary: A package for handling dataframes with optional backends.
Author: Joshua Sundance Bailey
Maintainer: Joshua Sundance Bailey
License: MIT
Project-URL: Repository, https://github.com/joshuasundance-swca/dataframe_handlers.git
Keywords: dataframe,interoperability
Classifier: License :: OSI Approved :: MIT License
Classifier: Programming Language :: Python
Classifier: Programming Language :: Python :: 3
Requires-Python: >=3.9
License-File: LICENSE
Provides-Extra: dask
Requires-Dist: dask[dataframe] ; extra == 'dask'
Requires-Dist: pandas ; extra == 'dask'
Provides-Extra: pandas
Requires-Dist: pandas ; extra == 'pandas'
Provides-Extra: xarray
Requires-Dist: xarray ; extra == 'xarray'
